shellviz/__init__.py
shellviz/cli.py
shellviz/client.py
shellviz/config.py
shellviz/django/__init__.py
shellviz/django/django_debug_toolbar.py
shellviz/django/logging.py
shellviz/django/timing_mixin.py
shellviz/server.py
shellviz/templates/shellviz/debug_toolbar_panel.html
shellviz/templatetags/__init__.py
shellviz/templatetags/shellviz.py
shellviz/utils.py
shellviz/utils_html.py
shellviz/utils_serialize.py
shellviz/utils_websockets.py
shellviz-0.5.0.dist-info/METADATA
shellviz-0.5.0.dist-info/WHEEL
shellviz-0.5.0.dist-info/entry_points.txt
shellviz-0.5.0.dist-info/RECORD
