Metadata-Version: 2.1
Name: shellviz
Version: 0.5.0
Summary: 
Author: Jean-Marc Skopek
Author-email: jskopek@gmail.com
Requires-Python: >=3.9,<4.0
Classifier: Programming Language :: Python :: 3
Classifier: Programming Language :: Python :: 3.9
Classifier: Programming Language :: Python :: 3.10
Classifier: Programming Language :: Python :: 3.11
